{
    "name": "BLOCK STRIPE POLO",
    "systemName": "BLOCK_STRIPE_POLO",
    "infoLink": "http:\/\/www.incuclothing.com\/shop-men\/designer\/lyle-scott\/block-stripe-polo-light-blue-marle\/",
    "description": "                 Lyle &amp; Scott polo shirt has a three button placket, short sleeves, small Golden Eagle badge on left chest, ribbed hem on sleeves, knit collar, small slits on sides, slim fitting, horizontal block stripes                                               Colour: Light Blue Marle                                                              ",
    "mainImage": "http:\/\/media.incuclothing.com\/cache\/65\/0b\/650b906a8e41b53a33c8d248a419ee9e.jpg",
    "moreImages": {
        "1": "http:\/\/media.incuclothing.com\/cache\/91\/9f\/919fcc79402d3449c89dc1a4afb0a15a.jpg",
        "2": "http:\/\/media.incuclothing.com\/cache\/d9\/a3\/d9a350783b288983349afe50aa4bb7e5.jpg",
        "3": "http:\/\/media.incuclothing.com\/cache\/9b\/c3\/9bc3fd145cf69459448b4babaeedf7a5.jpg",
        "4": "http:\/\/media.incuclothing.com\/cache\/30\/1c\/301c74f0d5442dbe66a7e49772edc533.jpg"
    },
    "price": "$50.00",
    "designer": "Lyle &amp; Scott",
    "allImgPaths": [
        "img\/Incu Men\/BLOCK_STRIPE_POLO_0.jpg",
        "img\/Incu Men\/\/BLOCK_STRIPE_POLO_1.jpg",
        "img\/Incu Men\/\/BLOCK_STRIPE_POLO_2.jpg",
        "img\/Incu Men\/\/BLOCK_STRIPE_POLO_3.jpg",
        "img\/Incu Men\/\/BLOCK_STRIPE_POLO_4.jpg"
    ],
    "store": "Incu Men",
    "category": "clothes",
    "spec_cat": "tshirts"
}