{
    "name": "GOOSE BOMBER JACKET",
    "systemName": "GOOSE_BOMBER_JACKET",
    "infoLink": "http:\/\/www.incuclothing.com\/shop-men\/designer\/saturdays-surf-nyc\/goose-bomber-jacket-olive\/",
    "description": "                 Saturdays Surf NYC bomber jacket has a full-zip with button closure placket, ribbed cuff, collar and bottom hem, snap closure pockets with nylon lining, internal pocket, contrast lining                                               Colour: Olive                                                              ",
    "mainImage": "http:\/\/media.incuclothing.com\/cache\/d3\/bf\/d3bfcda2560f9e21c7f3a220c7d54c45.jpg",
    "moreImages": {
        "1": "http:\/\/media.incuclothing.com\/cache\/b9\/14\/b9145fbef628202154b022847dcf7854.jpg",
        "2": "http:\/\/media.incuclothing.com\/cache\/dd\/ca\/ddca08a0b4ca927e5c4369fdc535282e.jpg",
        "3": "http:\/\/media.incuclothing.com\/cache\/b2\/28\/b2281ab6617b4b2e1f9358be1f7d392d.jpg",
        "4": "http:\/\/media.incuclothing.com\/cache\/08\/46\/0846f1736d9b491f051c4cbd59cdbb28.jpg"
    },
    "price": "$229.00",
    "designer": "Saturdays Surf NYC",
    "allImgPaths": [
        "img\/Incu Men\/GOOSE_BOMBER_JACKET_0.jpg",
        "img\/Incu Men\/\/GOOSE_BOMBER_JACKET_1.jpg",
        "img\/Incu Men\/\/GOOSE_BOMBER_JACKET_2.jpg",
        "img\/Incu Men\/\/GOOSE_BOMBER_JACKET_3.jpg",
        "img\/Incu Men\/\/GOOSE_BOMBER_JACKET_4.jpg"
    ],
    "store": "Incu Men",
    "category": "clothes",
    "spec_cat": "jackets"
}