{
    "name": "MILITARY JACKET",
    "systemName": "MILITARY_JACKET",
    "infoLink": "http:\/\/www.incuclothing.com\/shop-men\/designer\/oliver-spencer\/military-jacket-rye-green\/",
    "description": "                 Oliver Spencer military inspired jacket has a front button fastening, collar with removeable throat tab, long sleeves with single button cuffs and contrast elbow patches, patch pockets at chest with flap, vent pockets and patch pockets with flaps at hips, adjustable fixed belt                                               Colour: Rye Green                                                              ",
    "mainImage": "\/media\/cache\/82\/a3\/82a308d0a12d22022f78d43f939b6f22.jpg",
    "moreImages": {
        "1": "\/media\/cache\/3f\/ce\/3fce98c4e6bdd5b1a19c3f39fa48c734.jpg",
        "2": "\/media\/cache\/36\/61\/366140cc763819186254d08fc5888972.jpg",
        "3": "\/media\/cache\/c5\/b7\/c5b733547339440b0d6d19ff244f306d.jpg",
        "4": "\/media\/cache\/15\/2b\/152bf4952a500842d97569c5656fca3e.jpg",
        "5": "\/media\/cache\/cf\/3d\/cf3dd6c6721f4dafb461b80f765f488d.jpg"
    },
    "price": "$260.00",
    "designer": "Oliver Spencer",
    "allImgPaths": [
        "img\/Incu Men\/MILITARY_JACKET_0.jpg",
        "img\/Incu Men\/\/MILITARY_JACKET_1.jpg",
        "img\/Incu Men\/\/MILITARY_JACKET_2.jpg",
        "img\/Incu Men\/\/MILITARY_JACKET_3.jpg",
        "img\/Incu Men\/\/MILITARY_JACKET_4.jpg",
        "img\/Incu Men\/\/MILITARY_JACKET_5.jpg"
    ],
    "store": "Incu Men",
    "category": "clothes",
    "spec_cat": "jackets"
}