{
    "name": "POM POM BEANIE",
    "systemName": "POM_POM_BEANIE",
    "infoLink": "http:\/\/www.incuclothing.com\/shop-men\/designer\/saturdays-surf-nyc\/pom-pom-beanie-black\/",
    "description": "                 Saturdays Surf NYC knitted  woollen beanie has a fold up brim and stitched Saturdays logo on side, pom pom on top                                               Colour: Black                                                              ",
    "mainImage": "http:\/\/media.incuclothing.com\/cache\/e9\/25\/e925379df39de6ab9e34fead99c7afa2.jpg",
    "moreImages": {
        "1": "http:\/\/media.incuclothing.com\/cache\/a1\/65\/a16571de0ad1d56662842e4f47847a56.jpg"
    },
    "price": "$55.00",
    "designer": "Saturdays Surf NYC",
    "allImgPaths": [
        "img\/Incu Men\/POM_POM_BEANIE_0.jpg",
        "img\/Incu Men\/\/POM_POM_BEANIE_1.jpg"
    ],
    "store": "Incu Men",
    "category": "Accessories",
    "spec_cat": "accessories"
}