{
    "name": "REC SNEAKER",
    "systemName": "REC_SNEAKER",
    "infoLink": "http:\/\/www.incuclothing.com\/shop-men\/designer\/common-projects\/rec-sneaker-navy\/",
    "description": "                 Common Projects Rec Sneakers are low top shoes in nubuck suede, they have a round toe, lace ups, gold-toned serial number printed on side of shoe, white rubber sole, item fits large but narrow, recommend going down one size and laced loosely, shoes will stretch with wear                                               Colour: Navy                                                              ",
    "mainImage": "\/media\/cache\/c2\/5e\/c25e2acaf3e02c73fee7aa4518637225.jpg",
    "moreImages": {
        "1": "\/media\/cache\/33\/c1\/33c1ea4fd8fbf89cd17712bd55fc55f7.jpg",
        "2": "\/media\/cache\/68\/22\/6822dacfc3ab669260f109e37760b3f7.jpg",
        "3": "\/media\/cache\/2c\/1f\/2c1fcc849223210f7c86dd831f267430.jpg",
        "4": "\/media\/cache\/f5\/4e\/f54edc07256eb3e2c837625bb157b6eb.jpg"
    },
    "price": "$329.00",
    "designer": "Common Projects",
    "allImgPaths": [
        "img\/Incu Men\/REC_SNEAKER_0.jpg",
        "img\/Incu Men\/\/REC_SNEAKER_1.jpg",
        "img\/Incu Men\/\/REC_SNEAKER_2.jpg",
        "img\/Incu Men\/\/REC_SNEAKER_3.jpg",
        "img\/Incu Men\/\/REC_SNEAKER_4.jpg"
    ],
    "store": "Incu Men",
    "category": "shoes",
    "spec_cat": "shoes"
}