{
    "name": "Aros Heavy Chino Leaf",
    "systemName": "Aros_Heavy_Chino_Leaf",
    "infoLink": "http:\/\/www.uptherestore.com\/product\/aros-heavy-chino-leaf",
    "description": "Norse Projects Aros Heavy Chino. Leaf.",
    "mainImage": "http:\/\/www.uptherestore.com\/sites\/default\/files\/imagecache\/product_item\/norse-projects-ss13-aros-heavy-chino-leaf-1.jpg",
    "moreImages": [
        "\/sites\/default\/files\/norse-projects-ss13-aros-heavy-chino-leaf-2.jpg",
        "\/sites\/default\/files\/norse-projects-ss13-aros-heavy-chino-leaf-4.jpg",
        "\/sites\/default\/files\/norse-projects-ss13-aros-heavy-chino-leaf-4_0.jpg",
        "\/sites\/default\/files\/norse-projects-ss13-aros-heavy-chino-leaf-5.jpg"
    ],
    "price": "199.00AUD",
    "designer": "Norse Projects",
    "allImgPaths": [
        "img\/Up There\/Aros_Heavy_Chino_Leaf_0.jpg",
        "img\/Up There\/\/Aros_Heavy_Chino_Leaf_1.jpg",
        "img\/Up There\/\/Aros_Heavy_Chino_Leaf_2.jpg",
        "img\/Up There\/\/Aros_Heavy_Chino_Leaf_3.jpg",
        "img\/Up There\/\/Aros_Heavy_Chino_Leaf_4.jpg"
    ],
    "store": "Up There",
    "category": "clothes",
    "spec_cat": "pants"
}