{
    "name": "HEM TRIM POCKET TEE BLACK",
    "systemName": "HEM_TRIM_POCKET_TEE_BLACK",
    "infoLink": "http:\/\/www.uptherestore.com\/product\/hem-trim-pocket-tee-black",
    "description": "Tantum Hem Trim Pocket Tee. Black.",
    "mainImage": "http:\/\/www.uptherestore.com\/sites\/default\/files\/imagecache\/product_item\/tantum-ss13-hem-trim-pocket-tee-black-1.jpg",
    "moreImages": [
        "\/sites\/default\/files\/tantum-ss13-hem-trim-pocket-tee-black-2.jpg",
        "\/sites\/default\/files\/tantum-ss13-hem-trim-pocket-tee-black-3.jpg"
    ],
    "price": "65.00AUD",
    "designer": "Tantum",
    "allImgPaths": [
        "img\/Up There\/HEM_TRIM_POCKET_TEE_BLACK_0.jpg",
        "img\/Up There\/\/HEM_TRIM_POCKET_TEE_BLACK_1.jpg",
        "img\/Up There\/\/HEM_TRIM_POCKET_TEE_BLACK_2.jpg"
    ],
    "store": "Up There",
    "category": "clothes",
    "spec_cat": "tshirts"
}