{
    "name": "VACATION SHIRT CHAMBRAY",
    "systemName": "VACATION_SHIRT_CHAMBRAY",
    "infoLink": "http:\/\/www.uptherestore.com\/product\/vacation-shirt-chambray",
    "description": "Monitaly Vacation Shirt. Chambray.",
    "mainImage": "http:\/\/www.uptherestore.com\/sites\/default\/files\/imagecache\/product_item\/monitaly-ss13-vacation-shirt-chambray-1.jpg",
    "moreImages": [
        "\/sites\/default\/files\/monitaly-ss13-vacation-shirt-chambray-2.jpg",
        "\/sites\/default\/files\/monitaly-ss13-vacation-shirt-chambray-3.jpg"
    ],
    "price": "219.00AUD",
    "designer": "MONITALY",
    "allImgPaths": [
        "img\/Up There\/VACATION_SHIRT_CHAMBRAY_0.jpg",
        "img\/Up There\/\/VACATION_SHIRT_CHAMBRAY_1.jpg",
        "img\/Up There\/\/VACATION_SHIRT_CHAMBRAY_2.jpg"
    ],
    "store": "Up There",
    "category": "clothes",
    "spec_cat": "shirts"
}