{
    "name": "Wool Tie Navy Window Was $130, NOW",
    "systemName": "Wool_Tie_Navy_Window_Was_130_NOW",
    "infoLink": "http:\/\/www.uptherestore.com\/product\/wool-tie-navy-window-was-130-now",
    "description": "Monitaly Wool Tie. Navy Window.",
    "mainImage": "http:\/\/www.uptherestore.com\/sites\/default\/files\/imagecache\/product_item\/monitaly-fw12-wool-tie-navy-window-1.jpg",
    "moreImages": [
        "\/sites\/default\/files\/monitaly-fw12-wool-tie-navy-window-2.jpg",
        "\/sites\/default\/files\/monitaly-fw12-wool-tie-navy-window-3.jpg"
    ],
    "price": "65.00AUD",
    "designer": "MONITALY",
    "allImgPaths": [
        "img\/Up There\/Wool_Tie_Navy_Window_Was_130_NOW_0.jpg",
        "img\/Up There\/\/Wool_Tie_Navy_Window_Was_130_NOW_1.jpg",
        "img\/Up There\/\/Wool_Tie_Navy_Window_Was_130_NOW_2.jpg"
    ],
    "store": "Up There",
    "category": "accessories",
    "spec_cat": "Accessories"
}